<?xml version="1.0" encoding="UTF-8"?>
<channels>

  <!-- ================== ITALY ================== -->
  <channel site="raiplay.it"                      lang="it" xmltv_id="rai-1"       site_id="rai-1">Rai 1</channel>
  <channel site="raiplay.it"                      lang="it" xmltv_id="rai-2"       site_id="rai-2">Rai 2</channel>
  <channel site="raiplay.it"                      lang="it" xmltv_id="rai-3"       site_id="rai-3">Rai 3</channel>
  <channel site="mediasetinfinity.mediaset.it"    lang="it" xmltv_id="rete-4"      site_id="R4">Rete 4</channel>
  <channel site="mediasetinfinity.mediaset.it"    lang="it" xmltv_id="canale-5"    site_id="C5">Canale 5</channel>
  <channel site="mediasetinfinity.mediaset.it"    lang="it" xmltv_id="italia-1"    site_id="I1">Italia 1</channel>
  <channel site="guidatv.sky.it"                  lang="it" xmltv_id="tv2000"      site_id="DTH#7588">TV2000</channel>

  <!-- ================== USA ================== -->
  <channel site="tvtv.us"   lang="en" xmltv_id="abc-news-live"      site_id="113380">ABC News Live</channel>
  <channel site="tvtv.us"   lang="en" xmltv_id="livenowfromfox"     site_id="119219">LiveNOW from FOX</channel>

  <channel site="tvtv.us"   lang="en" xmltv_id="wabc"               site_id="20453">ABC 7</channel>
  <channel site="tvtv.us"   lang="en" xmltv_id="wnbc"               site_id="20459">NBC 4</channel>
  <channel site="tvtv.us"   lang="en" xmltv_id="wcbs"               site_id="16689">CBS 2</channel>
  <channel site="tvtv.us"   lang="en" xmltv_id="wnyw"               site_id="20360">FOX 5</channel>

  <channel site="tvtv.us"    lang="en" xmltv_id="bravo"             site_id="10057">Bravo</channel>
  <channel site="tvtv.us"    lang="en" xmltv_id="e-entertainment"   site_id="10989">E!</channel>
  <channel site="tvtv.us"    lang="en" xmltv_id="boomerang"         site_id="21883">Boomerang</channel>

  <channel site="tvtv.us"    lang="en" xmltv_id="espn"              site_id="10179">ESPN</channel>
  <channel site="tvtv.us"    lang="en" xmltv_id="espn2"             site_id="45507">ESPN2</channel>
  <channel site="tvtv.us"    lang="en" xmltv_id="espnu"             site_id="45654">ESPNU</channel>
  <channel site="tvtv.us"    lang="en" xmltv_id="acc-network"       site_id="111871">ACC Network</channel>
  <channel site="tvtv.us"    lang="en" xmltv_id="sec-network"       site_id="89535">SEC Network</channel>

</channels>
